{
  "name": "Màn Hình Trung Tâm Aqara MagicPad S1 Plus",
  "category": "central-control",
  "price": 9990000,
  "originalPrice": 11990000,
  "image": "/images/aqara-magicpad.jpg",
  "badge": null,
  "rating": 5,
  "reviews": 15,
  "description": "Màn hình cảm ứng 10 inch, điều khiển trung tâm nhà thông minh",
  "featured": false,
  "hotDeal": false,
  "newArrival": false,
  "sourceUrl": "https://thaihungsmarthome.com/san-pham/aqara-magicpad-s1",
  "sourceWebsite": "thaihungsmarthome.com",
  "specs": [
    "Màn hình 10\"",
    "Zigbee",
    "WiFi",
    "Cảm ứng"
  ]
}